emoles/__init__.py
emoles/constant.py
emoles/dptb.py
emoles/loss.py
emoles/mokit.py
emoles/multiwfn.py
emoles/py3Dmol.py
emoles/pyscf.py
emoles/utils.py
emoles-1.2.0.dist-info/licenses/LICENSE.txt
emoles-1.2.0.dist-info/METADATA
emoles-1.2.0.dist-info/WHEEL
emoles-1.2.0.dist-info/top_level.txt
emoles-1.2.0.dist-info/RECORD
