Metadata-Version: 2.4
Name: EMolES
Version: 1.2.0
Summary: A repo to calculate the electronic structures of electrolyte molecules.
Home-page: https://github.com/pyscaffold/pyscaffold/
Author: Franklalalala
Author-email: Liu Mingkang <1660810667@qq.com>
License: The MIT License (MIT)
Project-URL: Homepage, https://github.com/Franklalalala/EMolES
Project-URL: Bug Tracker, https://github.com/Franklalalala/EMolES/issues
Platform: any
Classifier: Programming Language :: Python :: 3
Classifier: License :: OSI Approved :: MIT License
Classifier: Intended Audience :: Science/Research
Requires-Python: >=3.8
License-File: LICENSE.txt
Requires-Dist: numpy
Requires-Dist: dptb
Requires-Dist: scipy
Requires-Dist: pyscf
Requires-Dist: scikit-learn
Requires-Dist: tqdm
Requires-Dist: torch
Requires-Dist: py3Dmol
Provides-Extra: dev
Requires-Dist: pytest>=6.0; extra == "dev"
Requires-Dist: pytest-cov; extra == "dev"
Requires-Dist: black; extra == "dev"
Requires-Dist: isort; extra == "dev"
Requires-Dist: flake8; extra == "dev"
Dynamic: license-file
